{
  "published": true,
  "validation": true,
  "location": "Lebanon",
  "ngo": "Dorcas",
  "titlePortal": {
    "en": "Dorcas-Tabitha cash aid program",
    "ar": "برنامج دوركاس طابيثا للمساعدات النقدية "
  },
  "titlePaApp": {
    "en": "Dorcas-Tabitha cash aid program",
    "ar": "برنامج دوركاس طابيثا للمساعدات النقدية "
  },
  "description": {
    "en": ""
  },
  "startDate": "2021-12-01T12:00:00Z",
  "endDate": "2022-06-30T12:00:00Z",
  "currency": "USD",
  "distributionFrequency": "month",
  "distributionDuration": 6,
  "fixedTransferValue": 50,
  "financialServiceProviders": [
    {
      "fsp": "BoB-finance"
    }
  ],
  "targetNrRegistrations": 340,
  "phoneNumberPlaceholder": "+251 000 000 000",
  "programCustomAttributes": [],
  "programQuestions": [
    {
      "name": "invited-by-dorcas",
      "answerType": "dropdown",
      "questionType": "standard",
      "options": [
        {
          "option": "yes",
          "label": {
            "en": "Yes",
            "ar": "نعم"
          }
        }
      ],
      "persistence": true,
      "export": ["all-people-affected", "included"],
      "scoring": {},
      "editableInPortal": false,
      "showInPeopleAffectedTable": false
    },
    {
      "name": "name",
      "label": {
        "en": "Name"
      },
      "answerType": "text",
      "questionType": "standard",
      "options": null,
      "persistence": true,
      "export": ["all-people-affected", "included"],
      "scoring": {},
      "editableInPortal": false,
      "showInPeopleAffectedTable": false
    },
    {
      "name": "age",
      "label": {
        "en": "Age"
      },
      "answerType": "numeric",
      "questionType": "standard",
      "options": null,
      "persistence": true,
      "export": ["all-people-affected", "included"],
      "scoring": {},
      "editableInPortal": false,
      "showInPeopleAffectedTable": false
    },
    {
      "name": "gender",
      "label": {
        "en": "Gender"
      },
      "answerType": "dropdown",
      "questionType": "standard",
      "options": [
        {
          "option": "male",
          "label": {
            "en": "Male",
            "ar": "ذكر"
          }
        },
        {
          "option": "female",
          "label": {
            "en": "Female",
            "ar": "أنثى"
          }
        }
      ],
      "persistence": true,
      "export": ["all-people-affected", "included"],
      "scoring": {},
      "editableInPortal": false,
      "showInPeopleAffectedTable": false
    },
    {
      "name": "nationality",
      "label": {
        "en": "Nationality"
      },
      "answerType": "dropdown",
      "questionType": "standard",
      "options": [
        {
          "option": "lebanese",
          "label": {
            "en": "Lebanese",
            "ar": "لبنانية"
          }
        },
        {
          "option": "syrian",
          "label": {
            "en": "Syrian",
            "ar": "سورية"
          }
        },
        {
          "option": "other",
          "label": {
            "en": "Other",
            "ar": "اُخرى"
          }
        }
      ],
      "persistence": true,
      "export": ["all-people-affected", "included"],
      "scoring": {},
      "editableInPortal": false,
      "showInPeopleAffectedTable": false
    },
    {
      "name": "address-city",
      "answerType": "text",
      "questionType": "standard",
      "options": null,
      "persistence": true,
      "export": ["all-people-affected", "included"],
      "scoring": {},
      "showInPeopleAffectedTable": false
    },
    {
      "name": "address-street",
      "label": {
        "en": "City"
      },
      "answerType": "text",
      "questionType": "standard",
      "options": null,
      "persistence": true,
      "export": ["all-people-affected", "included"],
      "scoring": {},
      "editableInPortal": false,
      "showInPeopleAffectedTable": false
    },
    {
      "name": "address-building",
      "label": {
        "en": "Building"
      },
      "answerType": "text",
      "questionType": "standard",
      "options": null,
      "persistence": true,
      "export": ["all-people-affected", "included"],
      "scoring": {},
      "editableInPortal": false,
      "showInPeopleAffectedTable": false
    },
    {
      "name": "address-floor",
      "label": {
        "en": "Floor"
      },
      "answerType": "text",
      "questionType": "standard",
      "options": null,
      "persistence": true,
      "export": ["all-people-affected", "included"],
      "scoring": {},
      "editableInPortal": false,
      "showInPeopleAffectedTable": false
    },
    {
      "name": "social-registry",
      "label": {
        "en": "Social registry number"
      },
      "answerType": "numeric",
      "questionType": "standard",
      "options": null,
      "persistence": true,
      "export": ["all-people-affected", "included"],
      "scoring": {},
      "editableInPortal": false,
      "showInPeopleAffectedTable": false
    },
    {
      "name": "family-status",
      "label": {
        "en": "Family status"
      },
      "answerType": "dropdown",
      "questionType": "standard",
      "options": [
        {
          "option": "married",
          "label": {
            "en": "Married",
            "ar": "متزوج"
          }
        },
        {
          "option": "single-no-children",
          "label": {
            "en": "Divorced/Single/Widow (no Children)",
            "ar": "مطلق/أعزب/أرمل ( لا أولاد)"
          }
        },
        {
          "option": "single-parent",
          "label": {
            "en": "Single parent",
            "ar": "مقدم(ة) الرعاية الوحيد(ة)"
          }
        },
        {
          "option": "child-headed",
          "label": {
            "en": "Child headed house hold",
            "ar": "أسرة يعيلها طفل "
          }
        }
      ],
      "persistence": true,
      "export": ["all-people-affected", "included"],
      "scoring": {
        "married": 0,
        "single-no-children": 1,
        "single-parent": 3,
        "child-headed": 6
      },
      "editableInPortal": false,
      "showInPeopleAffectedTable": false
    },
    {
      "name": "men-60+",
      "label": {
        "en": "Men 60+"
      },
      "answerType": "numeric",
      "questionType": "standard",
      "options": null,
      "persistence": true,
      "export": ["all-people-affected", "included"],
      "scoring": {
        "multiplier": 3
      },
      "editableInPortal": false,
      "showInPeopleAffectedTable": false
    },
    {
      "name": "women-60+",
      "label": {
        "en": "Women 60+"
      },
      "answerType": "numeric",
      "questionType": "standard",
      "options": null,
      "persistence": true,
      "export": ["all-people-affected", "included"],
      "scoring": {
        "multiplier": 3
      },
      "editableInPortal": false,
      "showInPeopleAffectedTable": false
    },
    {
      "name": "men-18-15",
      "label": {
        "en": "Men 18-59"
      },
      "answerType": "numeric",
      "questionType": "standard",
      "options": null,
      "persistence": true,
      "export": ["all-people-affected", "included"],
      "scoring": {
        "multiplier": 1
      },
      "editableInPortal": false,
      "showInPeopleAffectedTable": false
    },
    {
      "name": "women-18-59",
      "label": {
        "en": "Women 18-59"
      },
      "answerType": "numeric",
      "questionType": "standard",
      "options": null,
      "persistence": true,
      "export": ["all-people-affected", "included"],
      "scoring": {
        "multiplier": 1
      },
      "editableInPortal": false,
      "showInPeopleAffectedTable": false
    },
    {
      "name": "men-18-",
      "label": {
        "en": "Men 0-18"
      },
      "answerType": "numeric",
      "questionType": "standard",
      "options": null,
      "persistence": true,
      "export": ["all-people-affected", "included"],
      "scoring": {
        "multiplier": 2
      },
      "editableInPortal": false,
      "showInPeopleAffectedTable": false
    },
    {
      "name": "woman-18-",
      "label": {
        "en": "Women 0-18"
      },
      "answerType": "numeric",
      "questionType": "standard",
      "options": null,
      "persistence": true,
      "export": ["all-people-affected", "included"],
      "scoring": {
        "multiplier": 2
      },
      "editableInPortal": false,
      "showInPeopleAffectedTable": false
    },
    {
      "name": "woman-pregnant",
      "label": {
        "en": "Women pregnant"
      },
      "answerType": "dropdown",
      "questionType": "standard",
      "options": [
        {
          "option": "yes",
          "label": {
            "en": "Yes",
            "ar": "نعم"
          }
        },
        {
          "option": "no",
          "label": {
            "en": "No",
            "ar": "لا"
          }
        }
      ],
      "persistence": true,
      "export": ["all-people-affected", "included"],
      "scoring": {
        "yes": 2,
        "no": 0
      },
      "editableInPortal": false,
      "showInPeopleAffectedTable": false
    },
    {
      "name": "children-3-",
      "label": {
        "en": "Children"
      },
      "answerType": "dropdown",
      "questionType": "standard",
      "options": [
        {
          "option": "yes",
          "label": {
            "en": "Yes",
            "ar": "نعم"
          }
        },
        {
          "option": "no",
          "label": {
            "en": "No",
            "ar": "لا"
          }
        }
      ],
      "persistence": true,
      "export": ["all-people-affected", "included"],
      "scoring": {
        "yes": 2,
        "no": 0
      },
      "editableInPortal": false,
      "showInPeopleAffectedTable": false
    },
    {
      "name": "beirut-blast-affected",
      "label": {
        "en": "Beirut blast"
      },
      "answerType": "dropdown",
      "questionType": "standard",
      "options": [
        {
          "option": "yes",
          "label": {
            "en": "Yes",
            "ar": "نعم"
          }
        },
        {
          "option": "no",
          "label": {
            "en": "No",
            "ar": "لا"
          }
        }
      ],
      "persistence": true,
      "export": ["all-people-affected", "included"],
      "scoring": {
        "yes": 2,
        "no": 0
      },
      "editableInPortal": false,
      "showInPeopleAffectedTable": false
    },
    {
      "name": "beirut-blast-move",
      "label": {
        "en": "Forced moved"
      },
      "answerType": "dropdown",
      "questionType": "standard",
      "options": [
        {
          "option": "yes",
          "label": {
            "en": "Yes",
            "ar": "نعم"
          }
        },
        {
          "option": "no",
          "label": {
            "en": "No",
            "ar": "لا"
          }
        }
      ],
      "persistence": true,
      "export": ["all-people-affected", "included"],
      "scoring": {
        "yes": 2,
        "no": 0
      },
      "editableInPortal": false,
      "showInPeopleAffectedTable": false
    },
    {
      "name": "foster-family",
      "label": {
        "en": "Foster family"
      },
      "answerType": "dropdown",
      "questionType": "standard",
      "options": [
        {
          "option": "yes",
          "label": {
            "en": "Yes",
            "ar": "نعم"
          }
        },
        {
          "option": "no",
          "label": {
            "en": "No",
            "ar": "لا"
          }
        }
      ],
      "persistence": true,
      "export": ["all-people-affected", "included"],
      "scoring": {
        "yes": 2,
        "no": 0
      },
      "editableInPortal": false,
      "showInPeopleAffectedTable": false
    },
    {
      "name": "hospital-child",
      "label": {
        "en": "Children hospital"
      },
      "answerType": "dropdown",
      "questionType": "standard",
      "options": [
        {
          "option": "yes",
          "label": {
            "en": "Yes",
            "ar": "نعم"
          }
        },
        {
          "option": "no",
          "label": {
            "en": "No",
            "ar": "لا"
          }
        }
      ],
      "persistence": true,
      "export": ["all-people-affected", "included"],
      "scoring": {
        "yes": 4,
        "no": 0
      },
      "editableInPortal": false,
      "showInPeopleAffectedTable": false
    },
    {
      "name": "hospital-adult",
      "label": {
        "en": "Adult hospital"
      },
      "answerType": "dropdown",
      "questionType": "standard",
      "options": [
        {
          "option": "yes",
          "label": {
            "en": "Yes",
            "ar": "نعم"
          }
        },
        {
          "option": "no",
          "label": {
            "en": "No",
            "ar": "لا"
          }
        }
      ],
      "persistence": true,
      "export": ["all-people-affected", "included"],
      "scoring": {
        "yes": 2,
        "no": 0
      },
      "editableInPortal": false,
      "showInPeopleAffectedTable": false
    },
    {
      "name": "disability-adult-seeing",
      "label": {
        "en": "Disability seeing"
      },
      "answerType": "dropdown",
      "questionType": "standard",
      "options": [
        {
          "option": "no",
          "label": {
            "en": "No",
            "ar": "لا"
          }
        },
        {
          "option": "yes-some",
          "label": {
            "en": "Yes/Some difficulty",
            "ar": "نعم / بعض الصعوبة "
          }
        },
        {
          "option": "yes-lot",
          "label": {
            "en": "Yes/A lot of difficulty",
            "ar": "نعم / الكثير من الصعوبة"
          }
        },
        {
          "option": "yes-completely",
          "label": {
            "en": "Yes/Cannot do at all",
            "ar": "نعم / لا يمكن القيام به على الإطلاق "
          }
        }
      ],
      "persistence": true,
      "export": ["all-people-affected", "included"],
      "scoring": {
        "no": 0,
        "yes-some": 2,
        "yes-lot": 4,
        "yes-completely": 6
      },
      "editableInPortal": false,
      "showInPeopleAffectedTable": false
    },
    {
      "name": "disability-adult-hearing",
      "label": {
        "en": "Disability hearing"
      },
      "answerType": "dropdown",
      "questionType": "standard",
      "options": [
        {
          "option": "no",
          "label": {
            "en": "No",
            "ar": "لا"
          }
        },
        {
          "option": "yes-some",
          "label": {
            "en": "Yes/Some difficulty",
            "ar": "نعم / بعض الصعوبة "
          }
        },
        {
          "option": "yes-lot",
          "label": {
            "en": "Yes/A lot of difficulty",
            "ar": "نعم / الكثير من الصعوبة"
          }
        },
        {
          "option": "yes-completely",
          "label": {
            "en": "Yes/Cannot do at all",
            "ar": "نعم / لا يمكن القيام به على الإطلاق "
          }
        }
      ],
      "persistence": true,
      "export": ["all-people-affected", "included"],
      "scoring": {
        "no": 0,
        "yes-some": 2,
        "yes-lot": 4,
        "yes-completely": 6
      },
      "editableInPortal": false,
      "showInPeopleAffectedTable": false
    },
    {
      "name": "disability-adult-walking",
      "label": {
        "en": "Disability walking"
      },
      "answerType": "dropdown",
      "questionType": "standard",
      "options": [
        {
          "option": "no",
          "label": {
            "en": "No",
            "ar": "لا"
          }
        },
        {
          "option": "yes-some",
          "label": {
            "en": "Yes/Some difficulty",
            "ar": "نعم / بعض الصعوبة "
          }
        },
        {
          "option": "yes-lot",
          "label": {
            "en": "Yes/A lot of difficulty",
            "ar": "نعم / الكثير من الصعوبة"
          }
        },
        {
          "option": "yes-completely",
          "label": {
            "en": "Yes/Cannot do at all",
            "ar": "نعم / لا يمكن القيام به على الإطلاق "
          }
        }
      ],
      "persistence": true,
      "export": ["all-people-affected", "included"],
      "scoring": {
        "no": 0,
        "yes-some": 2,
        "yes-lot": 4,
        "yes-completely": 6
      },
      "editableInPortal": false,
      "showInPeopleAffectedTable": false
    },
    {
      "name": "disability-adult-remembering",
      "label": {
        "en": "Disability remembering"
      },
      "answerType": "dropdown",
      "questionType": "standard",
      "options": [
        {
          "option": "no",
          "label": {
            "en": "No",
            "ar": "لا"
          }
        },
        {
          "option": "yes-some",
          "label": {
            "en": "Yes/Some difficulty",
            "ar": "نعم / بعض الصعوبة "
          }
        },
        {
          "option": "yes-lot",
          "label": {
            "en": "Yes/A lot of difficulty",
            "ar": "نعم / الكثير من الصعوبة"
          }
        },
        {
          "option": "yes-completely",
          "label": {
            "en": "Yes/Cannot do at all",
            "ar": "نعم / لا يمكن القيام به على الإطلاق "
          }
        }
      ],
      "persistence": true,
      "export": ["all-people-affected", "included"],
      "scoring": {
        "no": 0,
        "yes-some": 2,
        "yes-lot": 4,
        "yes-completely": 6
      },
      "editableInPortal": false,
      "showInPeopleAffectedTable": false
    },
    {
      "name": "disability-adult-self-care",
      "label": {
        "en": "Disability self-care"
      },
      "answerType": "dropdown",
      "questionType": "standard",
      "options": [
        {
          "option": "no",
          "label": {
            "en": "No",
            "ar": "لا"
          }
        },
        {
          "option": "yes-some",
          "label": {
            "en": "Yes/Some difficulty",
            "ar": "نعم / بعض الصعوبة "
          }
        },
        {
          "option": "yes-lot",
          "label": {
            "en": "Yes/A lot of difficulty",
            "ar": "نعم / الكثير من الصعوبة"
          }
        },
        {
          "option": "yes-completely",
          "label": {
            "en": "Yes/Cannot do at all",
            "ar": "نعم / لا يمكن القيام به على الإطلاق "
          }
        }
      ],
      "persistence": true,
      "export": ["all-people-affected", "included"],
      "scoring": {
        "no": 0,
        "yes-some": 2,
        "yes-lot": 4,
        "yes-completely": 6
      },
      "editableInPortal": false,
      "showInPeopleAffectedTable": false
    },
    {
      "name": "disability-adult-self-communicating",
      "label": {
        "en": "Disability communicating"
      },
      "answerType": "dropdown",
      "questionType": "standard",
      "options": [
        {
          "option": "no",
          "label": {
            "en": "No",
            "ar": "لا"
          }
        },
        {
          "option": "yes-some",
          "label": {
            "en": "Yes/Some difficulty",
            "ar": "نعم / بعض الصعوبة "
          }
        },
        {
          "option": "yes-lot",
          "label": {
            "en": "Yes/A lot of difficulty",
            "ar": "نعم / الكثير من الصعوبة"
          }
        },
        {
          "option": "yes-completely",
          "label": {
            "en": "Yes/Cannot do at all",
            "ar": "نعم / لا يمكن القيام به على الإطلاق "
          }
        }
      ],
      "persistence": true,
      "export": ["all-people-affected", "included"],
      "scoring": {
        "no": 0,
        "yes-some": 2,
        "yes-lot": 4,
        "yes-completely": 6
      },
      "editableInPortal": false,
      "showInPeopleAffectedTable": false
    },
    {
      "name": "chronic-disease-child",
      "label": {
        "en": "Children chronic disease"
      },
      "answerType": "dropdown",
      "questionType": "standard",
      "options": [
        {
          "option": "yes",
          "label": {
            "en": "Yes",
            "ar": "نعم"
          }
        },
        {
          "option": "no",
          "label": {
            "en": "No",
            "ar": "لا"
          }
        }
      ],
      "persistence": true,
      "export": ["all-people-affected", "included"],
      "scoring": {
        "yes": 4,
        "no": 0
      },
      "editableInPortal": false,
      "showInPeopleAffectedTable": false
    },
    {
      "name": "chronic-disease-adult",
      "label": {
        "en": "Adult chronic disease"
      },
      "answerType": "dropdown",
      "questionType": "standard",
      "options": [
        {
          "option": "yes",
          "label": {
            "en": "Yes",
            "ar": "نعم"
          }
        },
        {
          "option": "no",
          "label": {
            "en": "No",
            "ar": "لا"
          }
        }
      ],
      "persistence": true,
      "export": ["all-people-affected", "included"],
      "scoring": {
        "yes": 2,
        "no": 0
      },
      "editableInPortal": false,
      "showInPeopleAffectedTable": false
    },
    {
      "name": "expenses-health",
      "label": {
        "en": "Health expenses"
      },
      "answerType": "dropdown",
      "questionType": "standard",
      "options": [
        {
          "option": "below-500000",
          "label": {
            "en": "Below 500.000 LBP",
            "ar": "أقل من 500.000 ليرة لبنانية "
          }
        },
        {
          "option": "500000-1000000",
          "label": {
            "en": "Between 500.000 and 1.000.000 LBP",
            "ar": "بين 500.000 و 1.000.000 ليرة لبنانية "
          }
        },
        {
          "option": "above-1000000",
          "label": {
            "en": "Above 1.000.000 LBP",
            "ar": "فوق 1.000.000 ليرة لبنانية "
          }
        }
      ],
      "persistence": true,
      "export": ["all-people-affected", "included"],
      "scoring": {
        "below-500000": 0,
        "500000-1000000": 1,
        "above-1000000": 2
      },
      "editableInPortal": false,
      "showInPeopleAffectedTable": false
    },
    {
      "name": "expenses-shelter",
      "label": {
        "en": "Shelter expenses"
      },
      "answerType": "dropdown",
      "questionType": "standard",
      "options": [
        {
          "option": "below-1000000",
          "label": {
            "en": "Below 1.000.000 LBP",
            "ar": "أقل من 1.000.000 ليرة لبنانية "
          }
        },
        {
          "option": "1000000-3000000",
          "label": {
            "en": "Between 1.000.000 and 3.000.000 LBP",
            "ar": "بين 1.000.000 و 3.000.000 ليرة لبنانية "
          }
        },
        {
          "option": "3000000-5000000",
          "label": {
            "en": "Between 3.000.000 and 5.000.000 LBP",
            "ar": "بين 3.000.000 و 5.000.000 ليرة لبنانية "
          }
        },
        {
          "option": "above-5000000",
          "label": {
            "en": "Above 5.000.000 LBP",
            "ar": "فوق 5.000.000 ليرة لبنانية "
          }
        }
      ],
      "persistence": true,
      "export": ["all-people-affected", "included"],
      "scoring": {
        "below-1000000": 2,
        "1000000-3000000": 4,
        "3000000-5000000": 6,
        "above-5000000": 8
      },
      "editableInPortal": false,
      "showInPeopleAffectedTable": false
    },
    {
      "name": "expenses-food",
      "label": {
        "en": "Food expenses"
      },
      "answerType": "dropdown",
      "questionType": "standard",
      "options": [
        {
          "option": "below-1000000",
          "label": {
            "en": "Below 1.000.000 LBP",
            "ar": "أقل من 1.000.000 ليرة لبنانية "
          }
        },
        {
          "option": "1000000-3000000",
          "label": {
            "en": "Between 1.000.000 and 3.000.000 LBP",
            "ar": "بين 1.000.000 و 3.000.000 ليرة لبنانية "
          }
        },
        {
          "option": "3000000-5000000",
          "label": {
            "en": "Between 3.000.000 and 5.000.000 LBP",
            "ar": "بين 3.000.000 و 5.000.000 ليرة لبنانية "
          }
        },
        {
          "option": "above-5000000",
          "label": {
            "en": "Above 5.000.000 LBP",
            "ar": "فوق 5.000.000 ليرة لبنانية "
          }
        }
      ],
      "persistence": true,
      "export": ["all-people-affected", "included"],
      "scoring": {
        "below-1000000": 2,
        "1000000-3000000": 4,
        "3000000-5000000": 6,
        "above-5000000": 8
      },
      "editableInPortal": false,
      "showInPeopleAffectedTable": false
    },
    {
      "name": "food-sold-assests",
      "label": {
        "en": "Sold household goods"
      },
      "answerType": "dropdown",
      "questionType": "standard",
      "options": [
        {
          "option": "yes",
          "label": {
            "en": "Yes",
            "ar": "نعم"
          }
        },
        {
          "option": "no",
          "label": {
            "en": "No",
            "ar": "لا"
          }
        }
      ],
      "persistence": true,
      "export": ["all-people-affected", "included"],
      "scoring": {
        "yes": 1,
        "no": 0
      },
      "editableInPortal": false,
      "showInPeopleAffectedTable": false
    },
    {
      "name": "food-spent-saving",
      "label": {
        "en": "Spend savings"
      },
      "answerType": "dropdown",
      "questionType": "standard",
      "options": [
        {
          "option": "yes",
          "label": {
            "en": "Yes",
            "ar": "نعم"
          }
        },
        {
          "option": "no",
          "label": {
            "en": "No",
            "ar": "لا"
          }
        }
      ],
      "persistence": true,
      "export": ["all-people-affected", "included"],
      "scoring": {
        "yes": 1,
        "no": 0
      },
      "editableInPortal": false,
      "showInPeopleAffectedTable": false
    },
    {
      "name": "food-borrowed-money",
      "label": {
        "en": "Borrowed money"
      },
      "answerType": "dropdown",
      "questionType": "standard",
      "options": [
        {
          "option": "yes",
          "label": {
            "en": "Yes",
            "ar": "نعم"
          }
        },
        {
          "option": "no",
          "label": {
            "en": "No",
            "ar": "لا"
          }
        }
      ],
      "persistence": true,
      "export": ["all-people-affected", "included"],
      "scoring": {
        "yes": 1,
        "no": 0
      },
      "editableInPortal": false,
      "showInPeopleAffectedTable": false
    },
    {
      "name": "food-recuded-expenses",
      "label": {
        "en": "Reduced expenses"
      },
      "answerType": "dropdown",
      "questionType": "standard",
      "options": [
        {
          "option": "yes",
          "label": {
            "en": "Yes",
            "ar": "نعم"
          }
        },
        {
          "option": "no",
          "label": {
            "en": "No",
            "ar": "لا"
          }
        }
      ],
      "persistence": true,
      "export": ["all-people-affected", "included"],
      "scoring": {
        "yes": 1,
        "no": 0
      },
      "editableInPortal": false,
      "showInPeopleAffectedTable": false
    },
    {
      "name": "food-withdraw-school",
      "label": {
        "en": "Withdraw food"
      },
      "answerType": "dropdown",
      "questionType": "standard",
      "options": [
        {
          "option": "yes",
          "label": {
            "en": "Yes",
            "ar": "نعم"
          }
        },
        {
          "option": "no",
          "label": {
            "en": "No",
            "ar": "لا"
          }
        }
      ],
      "persistence": true,
      "export": ["all-people-affected", "included"],
      "scoring": {
        "yes": 1,
        "no": 0
      },
      "editableInPortal": false,
      "showInPeopleAffectedTable": false
    },
    {
      "name": "food-child-labor",
      "label": {
        "en": "Child labor"
      },
      "answerType": "dropdown",
      "questionType": "standard",
      "options": [
        {
          "option": "yes",
          "label": {
            "en": "Yes",
            "ar": "نعم"
          }
        },
        {
          "option": "no",
          "label": {
            "en": "No",
            "ar": "لا"
          }
        }
      ],
      "persistence": true,
      "export": ["all-people-affected", "included"],
      "scoring": {
        "yes": 1,
        "no": 0
      },
      "editableInPortal": false,
      "showInPeopleAffectedTable": false
    },
    {
      "name": "food-household-migrated",
      "label": {
        "en": "Household migrated"
      },
      "answerType": "dropdown",
      "questionType": "standard",
      "options": [
        {
          "option": "yes",
          "label": {
            "en": "Yes",
            "ar": "نعم"
          }
        },
        {
          "option": "no",
          "label": {
            "en": "No",
            "ar": "لا"
          }
        }
      ],
      "persistence": true,
      "export": ["all-people-affected", "included"],
      "scoring": {
        "yes": 1,
        "no": 0
      },
      "editableInPortal": false,
      "showInPeopleAffectedTable": false
    },
    {
      "name": "food-sold-real-estate",
      "label": {
        "en": "Sold real estate"
      },
      "answerType": "dropdown",
      "questionType": "standard",
      "options": [
        {
          "option": "yes",
          "label": {
            "en": "Yes",
            "ar": "نعم"
          }
        },
        {
          "option": "no",
          "label": {
            "en": "No",
            "ar": "لا"
          }
        }
      ],
      "persistence": true,
      "export": ["all-people-affected", "included"],
      "scoring": {
        "yes": 1,
        "no": 0
      },
      "editableInPortal": false,
      "showInPeopleAffectedTable": false
    },
    {
      "name": "7-days-eat-less",
      "label": {
        "en": "Eating less"
      },
      "answerType": "dropdown",
      "questionType": "standard",
      "options": [
        {
          "option": "never",
          "label": {
            "en": "Never",
            "ar": "أبداً"
          }
        },
        {
          "option": "yes-1-2",
          "label": {
            "en": "1 or 2 days",
            "ar": "يوم أو يومين "
          }
        },
        {
          "option": "yes-3-4",
          "label": {
            "en": "3 or 4 days",
            "ar": "3 أو 4 أيام "
          }
        },
        {
          "option": "yes-5-6",
          "label": {
            "en": "5 or 6 days",
            "ar": "5 أو 6 أيام "
          }
        },
        {
          "option": "yes-7",
          "label": {
            "en": "7 days",
            "ar": "7 أيام"
          }
        }
      ],
      "persistence": true,
      "export": ["all-people-affected", "included"],
      "scoring": {
        "never": 0,
        "yes-1-2": 1,
        "yes-3-4": 2,
        "yes-5-6": 3,
        "yes-7": 4
      },
      "editableInPortal": false,
      "showInPeopleAffectedTable": false
    },
    {
      "name": "7-days-borrowed-food",
      "label": {
        "en": "Borrowed food"
      },
      "answerType": "dropdown",
      "questionType": "standard",
      "options": [
        {
          "option": "never",
          "label": {
            "en": "Never",
            "ar": "أبداً"
          }
        },
        {
          "option": "yes-1-2",
          "label": {
            "en": "1 or 2 days",
            "ar": "يوم أو يومين "
          }
        },
        {
          "option": "yes-3-4",
          "label": {
            "en": "3 or 4 days",
            "ar": "3 أو 4 أيام "
          }
        },
        {
          "option": "yes-5-6",
          "label": {
            "en": "5 or 6 days",
            "ar": "5 أو 6 أيام "
          }
        },
        {
          "option": "yes-7",
          "label": {
            "en": "7 days",
            "ar": "7 أيام"
          }
        }
      ],
      "persistence": true,
      "export": ["all-people-affected", "included"],
      "scoring": {
        "never": 0,
        "yes-1-2": 1,
        "yes-3-4": 2,
        "yes-5-6": 3,
        "yes-7": 4
      },
      "editableInPortal": false,
      "showInPeopleAffectedTable": false
    },
    {
      "name": "7-days-reduce-portions",
      "label": {
        "en": "Reduced portions"
      },
      "answerType": "dropdown",
      "questionType": "standard",
      "options": [
        {
          "option": "never",
          "label": {
            "en": "Never",
            "ar": "أبداً"
          }
        },
        {
          "option": "yes-1-2",
          "label": {
            "en": "1 or 2 days",
            "ar": "يوم أو يومين "
          }
        },
        {
          "option": "yes-3-4",
          "label": {
            "en": "3 or 4 days",
            "ar": "3 أو 4 أيام "
          }
        },
        {
          "option": "yes-5-6",
          "label": {
            "en": "5 or 6 days",
            "ar": "5 أو 6 أيام "
          }
        },
        {
          "option": "yes-7",
          "label": {
            "en": "7 days",
            "ar": "7 أيام"
          }
        }
      ],
      "persistence": true,
      "export": ["all-people-affected", "included"],
      "scoring": {
        "never": 0,
        "yes-1-2": 1,
        "yes-3-4": 2,
        "yes-5-6": 3,
        "yes-7": 4
      },
      "editableInPortal": false,
      "showInPeopleAffectedTable": false
    },
    {
      "name": "7-days-reduce-portions-adults",
      "label": {
        "en": "Reduced intake adults"
      },
      "answerType": "dropdown",
      "questionType": "standard",
      "options": [
        {
          "option": "never",
          "label": {
            "en": "Never",
            "ar": "أبداً"
          }
        },
        {
          "option": "yes-1-2",
          "label": {
            "en": "1 or 2 days",
            "ar": "يوم أو يومين "
          }
        },
        {
          "option": "yes-3-4",
          "label": {
            "en": "3 or 4 days",
            "ar": "3 أو 4 أيام "
          }
        },
        {
          "option": "yes-5-6",
          "label": {
            "en": "5 or 6 days",
            "ar": "5 أو 6 أيام "
          }
        },
        {
          "option": "yes-7",
          "label": {
            "en": "7 days",
            "ar": "7 أيام"
          }
        }
      ],
      "persistence": true,
      "export": ["all-people-affected", "included"],
      "scoring": {
        "never": 0,
        "yes-1-2": 1,
        "yes-3-4": 2,
        "yes-5-6": 3,
        "yes-7": 4
      },
      "editableInPortal": false,
      "showInPeopleAffectedTable": false
    },
    {
      "name": "7-days-reduce-nr-meals",
      "label": {
        "en": "Reduced meals"
      },
      "answerType": "dropdown",
      "questionType": "standard",
      "options": [
        {
          "option": "never",
          "label": {
            "en": "Never",
            "ar": "أبداً"
          }
        },
        {
          "option": "yes-1-2",
          "label": {
            "en": "1 or 2 days",
            "ar": "يوم أو يومين "
          }
        },
        {
          "option": "yes-3-4",
          "label": {
            "en": "3 or 4 days",
            "ar": "3 أو 4 أيام "
          }
        },
        {
          "option": "yes-5-6",
          "label": {
            "en": "5 or 6 days",
            "ar": "5 أو 6 أيام "
          }
        },
        {
          "option": "yes-7",
          "label": {
            "en": "7 days",
            "ar": "7 أيام"
          }
        }
      ],
      "persistence": true,
      "export": ["all-people-affected", "included"],
      "scoring": {
        "never": 0,
        "yes-1-2": 1,
        "yes-3-4": 2,
        "yes-5-6": 3,
        "yes-7": 4
      },
      "editableInPortal": false,
      "showInPeopleAffectedTable": false
    },
    {
      "name": "income",
      "label": {
        "en": "Household income"
      },
      "answerType": "dropdown",
      "questionType": "standard",
      "options": [
        {
          "option": "below-1000000",
          "label": {
            "en": "Below 1.000.000 LBP",
            "ar": "أقل من 1.000.000 ليرة لبنانية "
          }
        },
        {
          "option": "1000000-3000000",
          "label": {
            "en": "Between 1.000.000 and 3.000.000 LBP",
            "ar": "بين 1.000.000 و 3.000.000 ليرة لبنانية "
          }
        },
        {
          "option": "3000000-5000000",
          "label": {
            "en": "Between 3.000.000 and 5.000.000 LBP",
            "ar": "بين 3.000.000 و 5.000.000 ليرة لبنانية "
          }
        },
        {
          "option": "above-5000000",
          "label": {
            "en": "Above 5.000.000 LBP",
            "ar": "فوق 5.000.000 ليرة لبنانية "
          }
        }
      ],
      "persistence": true,
      "export": ["all-people-affected", "included"],
      "scoring": {
        "below-1000000": 4,
        "1000000-3000000": 3,
        "3000000-5000000": 2,
        "above-5000000": 1
      },
      "editableInPortal": false,
      "showInPeopleAffectedTable": false
    },
    {
      "name": "income-source",
      "label": {
        "en": "Income source"
      },
      "answerType": "dropdown",
      "questionType": "standard",
      "options": [
        {
          "option": "salary-regular",
          "label": {
            "en": "Salary for regular work",
            "ar": "الراتب عن العمل المنتظم "
          }
        },
        {
          "option": "salary-occasional",
          "label": {
            "en": "Salary for occasional work",
            "ar": "الراتب للعمل يومي أو متقطع"
          }
        },
        {
          "option": "savings",
          "label": {
            "en": "Savings",
            "ar": "مدخرات"
          }
        },
        {
          "option": "debts",
          "label": {
            "en": "Debts",
            "ar": "ديون"
          }
        },
        {
          "option": "gifts",
          "label": {
            "en": "Gifts",
            "ar": "هدايا "
          }
        },
        {
          "option": "remittances",
          "label": {
            "en": "Remittances",
            "ar": "التحويلات "
          }
        },
        {
          "option": "pension",
          "label": {
            "en": "Pension",
            "ar": "راتب تقاعد"
          }
        },
        {
          "option": "humanitarian-assistance",
          "label": {
            "en": "Humanitarian assistance",
            "ar": "مساعدات إنسانية"
          }
        }
      ],
      "persistence": true,
      "export": ["all-people-affected", "included"],
      "scoring": {
        "salary-regular": 1,
        "salary-occasional": 4,
        "savings": 2,
        "debts": 5,
        "gifts": 3,
        "remittances": 1,
        "pension": 2,
        "humanitarian-assistance": 4
      },
      "editableInPortal": false,
      "showInPeopleAffectedTable": false
    },
    {
      "name": "debt",
      "label": {
        "en": "Debt"
      },
      "answerType": "dropdown",
      "questionType": "standard",
      "options": [
        {
          "option": "no",
          "label": {
            "en": "I don’t have any debt",
            "ar": "ليس لدينا أي ديون "
          }
        },
        {
          "option": "below-1000000",
          "label": {
            "en": "Below 1.000.000 LBP",
            "ar": "أقل من 1.000.000 ليرة لبنانية "
          }
        },
        {
          "option": "1000000-3000000",
          "label": {
            "en": "Between 1.000.000 and 3.000.000 LBP",
            "ar": "بين 1.000.000 و 3.000.000 ليرة لبنانية "
          }
        },
        {
          "option": "3000000-5000000",
          "label": {
            "en": "Between 3.000.000 and 5.000.000 LBP",
            "ar": "بين 3.000.000 و 5.000.000 ليرة لبنانية "
          }
        },
        {
          "option": "above-5000000",
          "label": {
            "en": "Above 5.000.000 LBP",
            "ar": "فوق 5.000.000 ليرة لبنانية "
          }
        }
      ],
      "persistence": true,
      "export": ["all-people-affected", "included"],
      "scoring": {
        "below-1000000": 1,
        "1000000-3000000": 2,
        "3000000-5000000": 3,
        "above-5000000": 4,
        "no": 0
      },
      "editableInPortal": false,
      "showInPeopleAffectedTable": false
    },
    {
      "name": "other-help",
      "label": {
        "en": "Other help"
      },
      "answerType": "dropdown",
      "questionType": "standard",
      "options": [
        {
          "option": "yes",
          "label": {
            "en": "Yes",
            "ar": "نعم"
          }
        },
        {
          "option": "no",
          "label": {
            "en": "No",
            "ar": "لا"
          }
        }
      ],
      "persistence": true,
      "export": ["all-people-affected", "included"],
      "scoring": {
        "no": 4,
        "yes": 0
      },
      "editableInPortal": false,
      "showInPeopleAffectedTable": false
    },
    {
      "name": "where-register",
      "label": {
        "en": "Where registered"
      },
      "answerType": "dropdown",
      "questionType": "standard",
      "options": [
        {
          "option": "at-centre",
          "label": {
            "en": "At the centre",
            "ar": "في مركز"
          }
        },
        {
          "option": "self",
          "label": {
            "en": "Somewhere else",
            "ar": "مكان آخر"
          }
        }
      ],
      "persistence": true,
      "export": ["all-people-affected", "included"],
      "scoring": {},
      "editableInPortal": false,
      "showInPeopleAffectedTable": false
    },
    {
      "name": "name-social-worker",
      "label": {
        "en": "Social worker"
      },
      "answerType": "text",
      "questionType": "standard",
      "options": null,
      "persistence": true,
      "export": ["all-people-affected", "included"],
      "scoring": {},
      "editableInPortal": false,
      "showInPeopleAffectedTable": false
    }
  ],
  "aboutProgram": {
    "en": "This Dorcas-Tabitha cash aid program was created to support people living in Achrafieh and Batroun that experience difficulties in meeting their basic needs.<br><br>After registering for this project and answering questions, we may call you to make an appoint for a home visit to check your situation. After the home visit, we will send you an SMS to let you know if you are selected or not.<br><br>IF YOU ARE SELECTED the Dorcas-Tabitha cash aid program aims to help you:  <br> &bull; Until the Dorcas-Tabitha cash aid program ends, May 31, 2021.<br><br>IF YOU ARE SELECTED the Dorcas-Tabitha cash aid program will support you with the following:<br> &bull; A monthly cash grant of $50. You will receive an SMS from BoB finance. You can use this SMS and your ID card to pick up the cash grant at a BoB finance branch. <br><br>If you have any questions, feedback or a complaint please contact us via telephone or WhatsApp on one of the following phone numbers:  <br> &bull; Achrafieh: +961 81 232 710  <br> &bull; Batroun: +961 70 169 265  <br><br>You can also check our website:<br> &bull; www.tabithalb.org",
    "ar": "تم إنشاء برنامج دوركاس - طابيثا للمساعدات النقدية لدعم الأشخاص الذين يعيشون في الأشرفية والبترون الذين يواجهون صعوبات في تلبية احتياجاتهم الأساسية. بعد التسجيل في هذا المشروع والإجابة على الأسئلة ، قد نتصل بكم لتحديد موعد لزيارة منزلية للتحقق من وضعكم المعيشي. بعد الزيارة المنزلية ، سوف نرسل لكم رسالة نصية لإعلامكم إذا تم اختياركم أم لا ، حتى انتهاء برنامج المساعدة النقدية لدوركاس - طابيثا ، في 31  أيار 2021. إذا تم اختيارك ، فسوف يدعمكم برنامج المساعدة النقدية لدوركاس - طابيثا  بما يلي: & bull؛ منحة نقدية شهرية بقيمة 50 دولارًا. سوف تتلقى رسالة نصية قصيرة من BoB Finance. يمكنك استخدام هذه الرسالة النصية القصيرة وبطاقة الهوية الخاصة بك للحصول على المنحة النقدية من أحد فروع BoB Finance. إذا كانت لديك أي أسئلة أو ملاحظات أو شكوى ، فيرجى الاتصال بنا عبر الهاتف أو WhatsApp على أحد أرقام الهواتف التالية: & bull؛ الأشرفية:  96181232710+ & bull؛ البترون: 96170169265+ يمكنك أيضًا مراجعة موقعنا على الإنترنت: & bull؛ www.tabithalb.org "
  },
  "fullnameNamingConvention": ["nameFirst", "nameLast"],
  "languages": ["en", "ar"],
  "allowEmptyPhoneNumber": false
}
